monitor/__init__.py
monitor/sentry/__init__.py
monitor/sentry/_main.py
monitor_tool-0.1.0rc3.dist-info/METADATA
monitor_tool-0.1.0rc3.dist-info/WHEEL
monitor_tool-0.1.0rc3.dist-info/RECORD
