Metadata-Version: 2.1
Name: monitor-tool
Version: 0.1.0rc3
Summary: Monitor is a library for monitoring the performance of your application.
License: MIT
Author: haonv
Author-email: haonnguyen@prepedu.com
Requires-Python: >=3.9,<4.0
Classifier: License :: OSI Approved :: MIT License
Classifier: Programming Language :: Python :: 3
Classifier: Programming Language :: Python :: 3.9
Classifier: Programming Language :: Python :: 3.10
Classifier: Programming Language :: Python :: 3.11
Classifier: Programming Language :: Python :: 3.12
Requires-Dist: sentry-sdk (>=2.17.0,<3.0.0)
